redio/__init__.py
redio/bench.py
redio/commands.py
redio/conn.py
redio/conv.py
redio/exc.py
redio/highlevel.py
redio/protocol.py
redio/pubsub.py
redio-0.5.2.dist-info/METADATA
redio-0.5.2.dist-info/WHEEL
redio-0.5.2.dist-info/top_level.txt
redio-0.5.2.dist-info/RECORD
