Metadata-Version: 2.1
Name: redio
Version: 0.5.2
Summary: Redis async client for Trio
Home-page: https://github.com/Tronic/redio
Author: L. Kärkkäinen
Author-email: tronic@noreply.users.github.com
License: UNKNOWN
Keywords: Redis,key-value store,trio,async,database,networking
Platform: UNKNOWN
Classifier: Development Status :: 3 - Alpha
Classifier: Intended Audience :: Developers
Classifier: Programming Language :: Python :: 3
Classifier: Programming Language :: Python :: 3.7
Classifier: Programming Language :: Python :: 3.8
Classifier: Topic :: System :: Networking
Classifier: Framework :: Trio
Classifier: License :: OSI Approved :: MIT License
Classifier: License :: Public Domain
Classifier: Operating System :: OS Independent
Requires-Python: >=3.7
Requires-Dist: trio (>=0.13)
